bounciepy/__init__.py
bounciepy/async_rest_api_client.py
bounciepy/const.py
bounciepy/exceptions.py
bounciepy-0.3.0.dist-info/LICENSE
bounciepy-0.3.0.dist-info/METADATA
bounciepy-0.3.0.dist-info/WHEEL
bounciepy-0.3.0.dist-info/top_level.txt
bounciepy-0.3.0.dist-info/RECORD
