Metadata-Version: 2.1
Name: bounciepy
Version: 0.3.0
Summary: Python library to interact with bouncie.com API
Home-page: https://github.com/mandarons/bounciepy
Author: Mandar Patil
Author-email: mandarons@pm.me
Classifier: Programming Language :: Python :: 3
Classifier: Operating System :: OS Independent
Requires-Python: >=3.8
License-File: LICENSE
